{
  "__sender": "一颗豌豆芽",
  "__message": {
    "__type": "text",
    "__conn": "1",
    "__nnew": true
  },
  "__source": "聊天室1",
  "__date": 1641658768000
},
{
  "__sender": "一颗豌豆芽",
  "__message": {
    "__type": "text",
    "__conn": "1",
    "__nnew": true
  },
  "__source": "聊天室1",
  "__date": 1641658769000
},
{
  "__sender": "花心大萝卜",
  "__message": {
    "__type": "text",
    "__conn": "1",
    "__nnew": true
  },
  "__source": "聊天室1",
  "__date": 1641658771000
},
{
  "__sender": "花心大萝卜",
  "__message": {
    "__type": "text",
    "__conn": "1412",
    "__nnew": true
  },
  "__source": "聊天室1",
  "__date": 1641658773000
},
{
  "__sender": "花心大萝卜",
  "__message": {
    "__type": "text",
    "__conn": "12421",
    "__nnew": true
  },
  "__source": "聊天室1",
  "__date": 1641658785000
},
